ezeval/__init__.py
ezeval/ezevalib.py
ezeval-0.0.4.dist-info/LICENSE
ezeval-0.0.4.dist-info/METADATA
ezeval-0.0.4.dist-info/WHEEL
ezeval-0.0.4.dist-info/top_level.txt
ezeval-0.0.4.dist-info/RECORD
