Metadata-Version: 2.1
Name: ezeval
Version: 0.0.4
Summary: Library for easy marking.
Home-page: https://github.com/philencegold/ezeval
Author: philencegold
Author-email: 
Classifier: Programming Language :: Python :: 3
Classifier: License :: OSI Approved :: MIT License
License-File: LICENSE
Requires-Dist: PyPDF2
Requires-Dist: openpyxl
Requires-Dist: unidecode
